badvillain_greeting/__init__.py
badvillain_greeting/main.py
badvillain_python_package-1.4.0.dist-info/LICENSE
badvillain_python_package-1.4.0.dist-info/METADATA
badvillain_python_package-1.4.0.dist-info/WHEEL
badvillain_python_package-1.4.0.dist-info/top_level.txt
badvillain_python_package-1.4.0.dist-info/RECORD
