Metadata-Version: 2.1
Name: badvillain-python-package
Version: 1.4.0
Summary: Hello idk what to say
Home-page: https://www.thevillainer.tk/
Author: Badvillain
Author-email: idk@gmail.com
License: MIT
Platform: UNKNOWN
Classifier: License :: OSI Approved :: MIT License
Classifier: Programming Language :: Python :: 3
Classifier: Programming Language :: Python :: 3.7
